cache/__init__.py
cache/cache_config.py
cache/test/__init__.py
cache/test/test_cache_functionality.py
cache/test/test_cache_integration.py
light_pollution/__init__.py
light_pollution/light_pollution_analyzer.py
light_pollution/light_pollution_api.py
light_pollution/light_pollution_map.py
light_pollution/light_pollution_visualizer.py
light_pollution/public_api.py
light_pollution/resources/world_atlas/doc.kml
light_pollution/resources/world_atlas/doc.xml
light_pollution/resources/world_atlas/files/ArtificialSkyBrightness0.JPG
light_pollution/resources/world_atlas/files/ArtificialSkyBrightness1.JPG
light_pollution/resources/world_atlas/files/ArtificialSkyBrightness10.JPG
light_pollution/resources/world_atlas/files/ArtificialSkyBrightness100.JPG
light_pollution/resources/world_atlas/files/ArtificialSkyBrightness101.JPG
light_pollution/resources/world_atlas/files/ArtificialSkyBrightness102.JPG
light_pollution/resources/world_atlas/files/ArtificialSkyBrightness103.JPG
light_pollution/resources/world_atlas/files/ArtificialSkyBrightness104.JPG
light_pollution/resources/world_atlas/files/ArtificialSkyBrightness105.JPG
light_pollution/resources/world_atlas/files/ArtificialSkyBrightness106.JPG
light_pollution/resources/world_atlas/files/ArtificialSkyBrightness107.JPG
light_pollution/resources/world_atlas/files/ArtificialSkyBrightness108.JPG
light_pollution/resources/world_atlas/files/ArtificialSkyBrightness109.JPG
light_pollution/resources/world_atlas/files/ArtificialSkyBrightness11.JPG
light_pollution/resources/world_atlas/files/ArtificialSkyBrightness110.JPG
light_pollution/resources/world_atlas/files/ArtificialSkyBrightness111.JPG
light_pollution/resources/world_atlas/files/ArtificialSkyBrightness112.JPG
light_pollution/resources/world_atlas/files/ArtificialSkyBrightness113.JPG
light_pollution/resources/world_atlas/files/ArtificialSkyBrightness114.JPG
light_pollution/resources/world_atlas/files/ArtificialSkyBrightness115.JPG
stargazing_place_finder-0.3.1.dist-info/METADATA
stargazing_place_finder-0.3.1.dist-info/WHEEL
stargazing_place_finder-0.3.1.dist-info/entry_points.txt
stargazing_place_finder-0.3.1.dist-info/top_level.txt
stargazing_place_finder-0.3.1.dist-info/RECORD
