Metadata-Version: 2.4
Name: stargazing-place-finder
Version: 0.3.1
Summary: Stargazing place finder: light pollution analysis and stargazing area analytics
Author-email: StarGazer1995 <zhao.gong@outlook.com>
License: MIT
Keywords: stargazing,astronomy,light-pollution,geographic-analysis,location-finder
Classifier: Development Status :: 4 - Beta
Classifier: Intended Audience :: Developers
Classifier: Intended Audience :: Science/Research
Classifier: License :: OSI Approved :: MIT License
Classifier: Programming Language :: Python :: 3
Classifier: Programming Language :: Python :: 3.9
Classifier: Programming Language :: Python :: 3.10
Classifier: Programming Language :: Python :: 3.11
Classifier: Programming Language :: Python :: 3.12
Classifier: Topic :: Scientific/Engineering :: GIS
Classifier: Topic :: Scientific/Engineering :: Astronomy
Requires-Python: >=3.9
Requires-Dist: flask>=2.3.0
Requires-Dist: flask-cors>=4.0.0
Requires-Dist: folium>=0.14.0
Requires-Dist: matplotlib>=3.5.0
Requires-Dist: numpy>=1.21.0
Requires-Dist: pillow>=9.0.0
Requires-Dist: scipy>=1.7.0
Requires-Dist: osmnx>=1.3.0
Requires-Dist: networkx>=2.6.0
Requires-Dist: geopy>=2.2.0
Requires-Dist: psycopg2-binary>=2.9.0
Requires-Dist: requests>=2.25.0
Provides-Extra: dev
Requires-Dist: pytest>=7.0.0; extra == "dev"
Requires-Dist: pytest-cov>=4.0.0; extra == "dev"
Requires-Dist: requests-mock>=1.10.0; extra == "dev"
Requires-Dist: responses>=0.23.0; extra == "dev"
Requires-Dist: freezegun>=1.2.0; extra == "dev"
Requires-Dist: build>=0.10.0; extra == "dev"
Requires-Dist: twine>=4.0.0; extra == "dev"
